eimutils/__init__.py
eimutils/aws_secrets.py
eimutils/decrypt.py
eimutils/delogging.py
eimutils/snowflake_connection.py
eimutils/utils.py
eimutils-0.0.6.dist-info/METADATA
eimutils-0.0.6.dist-info/WHEEL
eimutils-0.0.6.dist-info/top_level.txt
eimutils-0.0.6.dist-info/RECORD
