Metadata-Version: 2.1
Name: eimutils
Version: 0.0.6
Summary: This project is a wrapper library to call utility functions.
Author: 
Author-email: 
Classifier: Programming Language :: Python :: 3
Classifier: License :: OSI Approved :: MIT License
Classifier: Operating System :: OS Independent
Requires-Python: >=3.9
